llama_index/tools/yelp/__init__.py
llama_index/tools/yelp/base.py
llama_index_tools_yelp-0.4.1.dist-info/METADATA
llama_index_tools_yelp-0.4.1.dist-info/WHEEL
llama_index_tools_yelp-0.4.1.dist-info/licenses/LICENSE
llama_index_tools_yelp-0.4.1.dist-info/RECORD
